sphinx_contributors/__init__.py
sphinx_contributors/_static/sphinx_contributors.css
sphinx_contributors-0.2.7.dist-info/LICENSE.md
sphinx_contributors-0.2.7.dist-info/WHEEL
sphinx_contributors-0.2.7.dist-info/METADATA
sphinx_contributors-0.2.7.dist-info/RECORD
