Metadata-Version: 2.1
Name: sphinx_contributors
Version: 0.2.7
Summary: Contributors extension for Sphinx.
Home-page: https://github.com/dgarcia360/sphinx-contributors
Author: David Garcia
Author-email: hi@davidgarcia.dev
Requires-Python: >=3.7
Classifier: Framework :: Sphinx :: Extension
Requires-Dist: sphinx >= 3
Requires-Dist: furo ; extra == "doc"
Requires-Dist: pre-commit ; extra == "test"
Requires-Dist: pytest ; extra == "test"
Provides-Extra: doc
Provides-Extra: test
